README.txt
setup.cfg
setup.py
abstract/__init__.py
abstract.jwrotator.egg-info/PKG-INFO
abstract.jwrotator.egg-info/SOURCES.txt
abstract.jwrotator.egg-info/dependency_links.txt
abstract.jwrotator.egg-info/entry_points.txt
abstract.jwrotator.egg-info/namespace_packages.txt
abstract.jwrotator.egg-info/not-zip-safe
abstract.jwrotator.egg-info/paster_plugins.txt
abstract.jwrotator.egg-info/requires.txt
abstract.jwrotator.egg-info/top_level.txt
abstract/jwrotator/__init__.py
abstract/jwrotator/configure.zcml
abstract/jwrotator/interfaces.py
abstract/jwrotator/profiles.zcml
abstract/jwrotator/setuphandlers.py
abstract/jwrotator/tests.py
abstract/jwrotator/version.txt
abstract/jwrotator/browser/__init__.py
abstract/jwrotator/browser/browser.py
abstract/jwrotator/browser/configure.zcml
abstract/jwrotator/portlets/__init__.py
abstract/jwrotator/portlets/configure.zcml
abstract/jwrotator/portlets/jwrotator_portlet.pt
abstract/jwrotator/portlets/jwrotator_portlet.py
abstract/jwrotator/profiles/default/import_steps.xml
abstract/jwrotator/profiles/default/jsregistry.xml
abstract/jwrotator/profiles/default/portlets.xml
abstract/jwrotator/profiles/default/skins.xml
abstract/jwrotator/skins/jwrotator_templates/imagerotator.swf
abstract/jwrotator/skins/jwrotator_templates/jwr_view.pt
abstract/jwrotator/skins/jwrotator_templates/swfobject.js
docs/HISTORY.txt
docs/INSTALL.txt
docs/LICENSE.GPL
docs/LICENSE.txt
