Metadata-Version: 1.0
Name: abstract.jwrotator
Version: 0.3
Summary: UNKNOWN
Home-page: http://www.abstract.it/svn
Author: Antonio Sagliocco (Abstract)
Author-email: antonio.sagliocco@abstract.it
License: GPL
Platform: UNKNOWN
Classifier: Framework :: Plone
Classifier: Programming Language :: Python
Classifier: Topic :: Software Development :: Libraries :: Python Modules
